automake/__init__.py
automake/__main__.py
automake/agent/__init__.py
automake/agent/manager.py
automake/agent/specialists.py
automake/agent/ui/__init__.py
automake/agent/ui/session.py
automake/cli/__init__.py
automake/cli/app.py
automake/cli/error_handler.py
automake/cli/logs.py
automake/cli/commands/__init__.py
automake/cli/commands/agent.py
automake/cli/commands/config.py
automake/cli/commands/init.py
automake/cli/commands/logs.py
automake/cli/commands/run.py
automake/cli/display/__init__.py
automake/cli/display/callbacks.py
automake/cli/display/help.py
automake/config/__init__.py
automake/config/defaults.py
automake/config/manager.py
automake/core/__init__.py
automake/core/ai_agent.py
automake/core/command_runner.py
automake/core/interactive.py
automake/core/makefile_reader.py
automake/logging/__init__.py
automake/logging/handlers.py
automake/logging/setup.py
automake/resources/ascii_art.txt
automake/utils/__init__.py
automake/utils/animation.py
automake/utils/model_selector.py
automake/utils/ollama_manager.py
automake/utils/output/__init__.py
automake/utils/output/formatter.py
automake/utils/output/live_box.py
automake/utils/output/types.py
automake_cli-0.4.8.dist-info/METADATA
automake_cli-0.4.8.dist-info/WHEEL
automake_cli-0.4.8.dist-info/entry_points.txt
automake_cli-0.4.8.dist-info/licenses/LICENSE
automake_cli-0.4.8.dist-info/RECORD
