Metadata-Version: 2.4
Name: automake-cli
Version: 0.4.8
Summary: The AI-native shell that turns natural language into actions.
Project-URL: Homepage, https://github.com/seanbaufeld/auto-make
Project-URL: Repository, https://github.com/seanbaufeld/auto-make
Project-URL: Issues, https://github.com/seanbaufeld/auto-make/issues
Author-email: Sean Baufeld <sean.baufeld@protonmail.com>
License:                                  Apache License
License-File: LICENSE
Keywords: ai,automation,cli,llm,makefile
Classifier: Development Status :: 3 - Alpha
Classifier: Environment :: Console
Classifier: Intended Audience :: Developers
Classifier: License :: OSI Approved :: MIT License
Classifier: Operating System :: OS Independent
Classifier: Programming Language :: Python :: 3
Classifier: Programming Language :: Python :: 3.13
Classifier: Topic :: Software Development :: Build Tools
Classifier: Topic :: Utilities
Requires-Python: >=3.13
Requires-Dist: appdirs>=1.4.4
Requires-Dist: duckduckgo-search>=8.0.4
Requires-Dist: ollama>=0.5.1
Requires-Dist: questionary>=2.0.1
Requires-Dist: requests>=2.31.0
Requires-Dist: rich>=13.0.0
Requires-Dist: smolagents[litellm]>=0.1.0
Requires-Dist: tomli-w>=1.0.0
Requires-Dist: typer>=0.9.0
Provides-Extra: dev
Requires-Dist: pre-commit>=4.2.0; extra == 'dev'
Requires-Dist: pytest-asyncio>=1.0.0; extra == 'dev'
Requires-Dist: pytest-cov>=4.1.0; extra == 'dev'
Requires-Dist: pytest-mock>=3.11.0; extra == 'dev'
Requires-Dist: pytest-timeout>=2.3.1; extra == 'dev'
Requires-Dist: pytest>=7.4.0; extra == 'dev'
Requires-Dist: pyyaml>=6.0.0; extra == 'dev'
Requires-Dist: ruff>=0.11.2; extra == 'dev'
